trem/__init__.py
trem-0.0.0.dist-info/LICENSE
trem-0.0.0.dist-info/METADATA
trem-0.0.0.dist-info/WHEEL
trem-0.0.0.dist-info/top_level.txt
trem-0.0.0.dist-info/RECORD
