Metadata-Version: 2.1
Name: trem
Version: 0.0.0
Summary: Trem: Um framework inovador.
Home-page: https://github.com/ArturArantes/trem
Author: Artur Arantes Santos da Silva
Author-email: contact@trembao.dev
Classifier: Programming Language :: Python :: 3
Classifier: License :: OSI Approved :: MIT License
Classifier: Operating System :: OS Independent
Requires-Python: >=3.6
License-File: LICENSE
